eastnine01/__init__.py
eastnine01/__main__.py
eastnine01-1.0.5.dist-info/METADATA
eastnine01-1.0.5.dist-info/WHEEL
eastnine01-1.0.5.dist-info/entry_points.txt
eastnine01-1.0.5.dist-info/licenses/LICENSE
eastnine01-1.0.5.dist-info/RECORD
