Metadata-Version: 2.4
Name: eastnine01
Version: 1.0.5
Summary: sample mcp tool
Project-URL: Homepage, https://github.com/dongkoo/eastnine01
Project-URL: Repository, https://github.com/dongkoo/eastnine01.git
Author-email: dongkoo <cef_tera@naver.com>
License: MIT
License-File: LICENSE
Classifier: Development Status :: 3 - Alpha
Classifier: Intended Audience :: Developers
Classifier: License :: OSI Approved :: MIT License
Classifier: Programming Language :: Python :: 3
Classifier: Programming Language :: Python :: 3.13
Classifier: Topic :: Communications
Classifier: Topic :: Internet
Classifier: Topic :: Software Development :: Libraries :: Python Modules
Requires-Python: >=3.13
Requires-Dist: build>=1.3.0
Requires-Dist: mcp[cli]>=1.12.4
